monaco_xnei/__init__.py
monaco_xnei/customtkinter_editor.py
monaco_xnei/pyqt_editor.py
monaco_xnei/tkinter_editor.py
monaco_xnei-0.0.3.dist-info/METADATA
monaco_xnei-0.0.3.dist-info/WHEEL
monaco_xnei-0.0.3.dist-info/top_level.txt
monaco_xnei-0.0.3.dist-info/RECORD
