Metadata-Version: 2.4
Name: monaco_xnei
Version: 0.0.3
Summary: You can import tkinter, customtkinter, and pyqt from the monaco-xnei library to use them in your Python projects.
Author: Your Name
Requires-Python: >=3.8
Requires-Dist: customtkinter
Requires-Dist: PyQt6
Requires-Dist: pygments
Dynamic: author
Dynamic: description
Dynamic: description-content-type
Dynamic: requires-dist
Dynamic: requires-python
Dynamic: summary
